alpss_processor/__init__.py
alpss_processor/alpss_stream_processor.py
alpss_processor-0.1.0.dist-info/METADATA
alpss_processor-0.1.0.dist-info/WHEEL
alpss_processor-0.1.0.dist-info/entry_points.txt
alpss_processor-0.1.0.dist-info/RECORD
