Metadata-Version: 2.4
Name: alpss-processor
Version: 0.1.0
Summary: Package to run ALPSS as a stream processor using openmsistream tools
Author: Ali Rachidi
Author-email: arachid1@jhu.edu
Requires-Python: >=3.9,<3.11
Classifier: Programming Language :: Python :: 3
Classifier: Programming Language :: Python :: 3.9
Classifier: Programming Language :: Python :: 3.10
Requires-Dist: alpss (==1.3.2)
Requires-Dist: openmsistream (==1.8.3.7.dev4)
Requires-Dist: openmsitoolbox (==1.2.5.dev1)
